{
  "dataset_id": "fe2c8cc2-83ae-4059-8011-96c8f2e81150",
  "original_filename": "diabetes.csv",
  "status": "processing",
  "row_count": 768,
  "column_count": 9,
  "columns": [
    "Pregnancies",
    "Glucose",
    "BloodPressure",
    "SkinThickness",
    "Insulin",
    "BMI",
    "DiabetesPedigreeFunction",
    "Age",
    "Outcome"
  ],
  "dtypes": {
    "Pregnancies": "int64",
    "Glucose": "int64",
    "BloodPressure": "int64",
    "SkinThickness": "int64",
    "Insulin": "int64",
    "BMI": "float64",
    "DiabetesPedigreeFunction": "float64",
    "Age": "int64",
    "Outcome": "int64"
  },
  "sample_rows": [
    {
      "Pregnancies": 6,
      "Glucose": 148,
      "BloodPressure": 72,
      "SkinThickness": 35,
      "Insulin": 0,
      "BMI": 33.6,
      "DiabetesPedigreeFunction": 0.627,
      "Age": 50,
      "Outcome": 1
    },
    {
      "Pregnancies": 1,
      "Glucose": 85,
      "BloodPressure": 66,
      "SkinThickness": 29,
      "Insulin": 0,
      "BMI": 26.6,
      "DiabetesPedigreeFunction": 0.351,
      "Age": 31,
      "Outcome": 0
    },
    {
      "Pregnancies": 8,
      "Glucose": 183,
      "BloodPressure": 64,
      "SkinThickness": 0,
      "Insulin": 0,
      "BMI": 23.3,
      "DiabetesPedigreeFunction": 0.672,
      "Age": 32,
      "Outcome": 1
    },
    {
      "Pregnancies": 1,
      "Glucose": 89,
      "BloodPressure": 66,
      "SkinThickness": 23,
      "Insulin": 94,
      "BMI": 28.1,
      "DiabetesPedigreeFunction": 0.167,
      "Age": 21,
      "Outcome": 0
    },
    {
      "Pregnancies": 0,
      "Glucose": 137,
      "BloodPressure": 40,
      "SkinThickness": 35,
      "Insulin": 168,
      "BMI": 43.1,
      "DiabetesPedigreeFunction": 2.288,
      "Age": 33,
      "Outcome": 1
    }
  ],
  "domain": "healthcare",
  "domain_details": {
    "domain": "healthcare",
    "sub_domain": "patient_records",
    "confidence": 0.9,
    "likely_questions": [
      "What are the risk factors for diabetes?",
      "How does pregnancy affect diabetes?",
      "Can we predict diabetes based on these variables?"
    ],
    "key_metrics": [
      "Diabetes prediction accuracy",
      "Average BMI of patients with diabetes",
      "Correlation between glucose levels and diabetes"
    ],
    "reasoning": "The presence of medical variables such as BloodPressure, SkinThickness, Insulin, and DiabetesPedigreeFunction, along with the Outcome column indicating the presence or absence of diabetes, suggests a strong connection to the healthcare domain, specifically patient records."
  },
  "profiling_report": {
    "total_rows": 768,
    "total_columns": 9,
    "columns": [
      "Pregnancies",
      "Glucose",
      "BloodPressure",
      "SkinThickness",
      "Insulin",
      "BMI",
      "DiabetesPedigreeFunction",
      "Age",
      "Outcome"
    ],
    "dtypes": {
      "Pregnancies": "int64",
      "Glucose": "int64",
      "BloodPressure": "int64",
      "SkinThickness": "int64",
      "Insulin": "int64",
      "BMI": "float64",
      "DiabetesPedigreeFunction": "float64",
      "Age": "int64",
      "Outcome": "int64"
    },
    "missing_values": {},
    "duplicates": {
      "count": 0,
      "percentage": 0.0,
      "has_duplicates": false
    },
    "outliers": {
      "Pregnancies": {
        "count": 4,
        "percentage": 0.52,
        "lower_bound": -6.5,
        "upper_bound": 13.5,
        "min_value": 0.0,
        "max_value": 17.0
      },
      "Glucose": {
        "count": 5,
        "percentage": 0.65,
        "lower_bound": 37.125,
        "upper_bound": 202.125,
        "min_value": 0.0,
        "max_value": 199.0
      },
      "BloodPressure": {
        "count": 45,
        "percentage": 5.86,
        "lower_bound": 35.0,
        "upper_bound": 107.0,
        "min_value": 0.0,
        "max_value": 122.0
      },
      "SkinThickness": {
        "count": 1,
        "percentage": 0.13,
        "lower_bound": -48.0,
        "upper_bound": 80.0,
        "min_value": 0.0,
        "max_value": 99.0
      },
      "Insulin": {
        "count": 34,
        "percentage": 4.43,
        "lower_bound": -190.875,
        "upper_bound": 318.125,
        "min_value": 0.0,
        "max_value": 846.0
      },
      "BMI": {
        "count": 19,
        "percentage": 2.47,
        "lower_bound": 13.35,
        "upper_bound": 50.55,
        "min_value": 0.0,
        "max_value": 67.1
      },
      "DiabetesPedigreeFunction": {
        "count": 29,
        "percentage": 3.78,
        "lower_bound": -0.33,
        "upper_bound": 1.2,
        "min_value": 0.078,
        "max_value": 2.42
      },
      "Age": {
        "count": 9,
        "percentage": 1.17,
        "lower_bound": -1.5,
        "upper_bound": 66.5,
        "min_value": 21.0,
        "max_value": 81.0
      }
    },
    "type_issues": {},
    "constant_columns": [],
    "high_cardinality": {},
    "quality_score": 80.0,
    "issues_count": 8
  },
  "quality_score": 80.0,
  "quality_summary": "Your data has a quality score of 80.0/100. Here's what we found:\n\u2022 Some unusual values were found in: Pregnancies, Glucose",
  "cleaning_plan": [
    {
      "action": "cap_outliers",
      "column": "Pregnancies",
      "lower": -6,
      "upper": 13
    },
    {
      "action": "cap_outliers",
      "column": "Glucose",
      "lower": 37,
      "upper": 202
    },
    {
      "action": "cap_outliers",
      "column": "BloodPressure",
      "lower": 35,
      "upper": 107
    },
    {
      "action": "cap_outliers",
      "column": "SkinThickness",
      "lower": 0,
      "upper": 80
    },
    {
      "action": "cap_outliers",
      "column": "Insulin",
      "lower": -190,
      "upper": 318
    },
    {
      "action": "cap_outliers",
      "column": "BMI",
      "lower": 13,
      "upper": 50
    },
    {
      "action": "cap_outliers",
      "column": "DiabetesPedigreeFunction",
      "lower": -0.33,
      "upper": 1.2
    },
    {
      "action": "cap_outliers",
      "column": "Age",
      "lower": 0,
      "upper": 66
    }
  ],
  "cleaning_report": {
    "actions_applied": [
      {
        "action": "cap_outliers",
        "column": "Pregnancies",
        "lower": -6,
        "upper": 13
      },
      {
        "action": "cap_outliers",
        "column": "Glucose",
        "lower": 37,
        "upper": 202
      },
      {
        "action": "cap_outliers",
        "column": "BloodPressure",
        "lower": 35,
        "upper": 107
      },
      {
        "action": "cap_outliers",
        "column": "SkinThickness",
        "lower": 0,
        "upper": 80
      },
      {
        "action": "cap_outliers",
        "column": "Insulin",
        "lower": -190,
        "upper": 318
      },
      {
        "action": "cap_outliers",
        "column": "BMI",
        "lower": 13,
        "upper": 50
      },
      {
        "action": "cap_outliers",
        "column": "DiabetesPedigreeFunction",
        "lower": -0.33,
        "upper": 1.2
      },
      {
        "action": "cap_outliers",
        "column": "Age",
        "lower": 0,
        "upper": 66
      }
    ],
    "actions_skipped": [],
    "rows_before": 768,
    "rows_after": 768,
    "columns_before": 9,
    "columns_after": 9,
    "rows_removed": 0,
    "columns_removed": 0
  },
  "cleaning_summary": "We cleaned your dataset with 8 improvements:\n\u2022 Corrected extreme values in 'Pregnancies'\n\u2022 Corrected extreme values in 'Glucose'\n\u2022 Corrected extreme values in 'BloodPressure'\n\u2022 Corrected extreme values in 'SkinThickness'\n\u2022 Corrected extreme values in 'Insulin'\n\u2022 Corrected extreme values in 'BMI'\n\u2022 Corrected extreme values in 'DiabetesPedigreeFunction'\n\u2022 Corrected extreme values in 'Age'",
  "is_cleaned": true,
  "has_embeddings": true,
  "rag_info": {
    "chunks_count": 49,
    "index_path": "./datasets\\fe2c8cc2-83ae-4059-8011-96c8f2e81150\\index.faiss",
    "chunks_path": "./datasets\\fe2c8cc2-83ae-4059-8011-96c8f2e81150\\chunks.pkl",
    "embedding_dim": 256
  },
  "dashboard": {
    "dataset_id": "fe2c8cc2-83ae-4059-8011-96c8f2e81150",
    "domain": "healthcare",
    "tile_count": 7,
    "tiles": [
      {
        "id": "kpi_shape",
        "type": "kpi",
        "title": "Dataset size",
        "value": "768",
        "unit": "rows",
        "sub": "9 columns",
        "color": "teal",
        "insight": "Your dataset contains 768 rows across 9 columns. This is a good-sized dataset for meaningful analysis."
      },
      {
        "id": "kpi_Pregnancies",
        "type": "kpi",
        "title": "Avg Pregnancies",
        "value": "3.83",
        "unit": "",
        "sub": "min 0  \u00b7  max 13",
        "color": "blue",
        "insight": "The typical pregnancies across the dataset is 3.83. min 0  \u00b7  max 13."
      },
      {
        "id": "kpi_missing",
        "type": "kpi",
        "title": "Missing values",
        "value": "0",
        "unit": "cells",
        "sub": "0.0% of dataset",
        "color": "green",
        "insight": "All values are present \u2014 no missing data detected. Your dataset is complete and ready for analysis."
      },
      {
        "id": "dist_Pregnancies",
        "type": "bar",
        "title": "Pregnancies distribution",
        "chart_data": {
          "labels": [
            "0.00",
            "1.08",
            "2.17",
            "3.25",
            "4.33",
            "5.42",
            "6.50",
            "7.58",
            "8.67",
            "9.75",
            "10.83",
            "11.92"
          ],
          "datasets": [
            {
              "label": "Count",
              "data": [
                246,
                103,
                75,
                68,
                57,
                50,
                45,
                38,
                28,
                24,
                11,
                23
              ]
            }
          ]
        },
        "color_scheme": "teal",
        "insight": "The majority of pregnancies are clustered around 0.00, with a steady decline in numbers as we move further away from this value. This suggests that most pregnancies are single, with fewer multiple pregnancies occurring in the data."
      },
      {
        "id": "correlation",
        "type": "bar",
        "title": "Correlation with Pregnancies",
        "chart_data": {
          "labels": [
            "Glucose",
            "BloodPressure",
            "SkinThickness",
            "Insulin",
            "BMI"
          ],
          "datasets": [
            {
              "label": "r",
              "data": [
                0.129,
                0.185,
                -0.085,
                -0.078,
                0.025
              ]
            }
          ]
        },
        "options": {
          "yMin": -1,
          "yMax": 1
        },
        "color_scheme": "purple",
        "insight": "BloodPressure is weakly linked to Pregnancies, but the relationship is not very strong. This suggests that BloodPressure is not a major factor in determining the number of Pregnancies."
      },
      {
        "id": "kpi_complete",
        "type": "kpi",
        "title": "Data completeness",
        "value": "100%",
        "unit": "",
        "sub": "No missing values",
        "color": "green",
        "insight": "Every cell in your dataset has a value \u2014 nothing is missing. This means all analysis will use the full dataset."
      },
      {
        "id": "top_Pregnancies",
        "type": "table",
        "title": "Top 10 by Pregnancies",
        "columns": [
          "Pregnancies",
          "Glucose",
          "BloodPressure",
          "SkinThickness",
          "Insulin",
          "BMI"
        ],
        "rows": [
          {
            "Pregnancies": 13.0,
            "Glucose": 145.0,
            "BloodPressure": 82.0,
            "SkinThickness": 19.0,
            "Insulin": 110.0,
            "BMI": 22.2
          },
          {
            "Pregnancies": 13.0,
            "Glucose": 126.0,
            "BloodPressure": 90.0,
            "SkinThickness": 0.0,
            "Insulin": 0.0,
            "BMI": 43.4
          },
          {
            "Pregnancies": 13.0,
            "Glucose": 106.0,
            "BloodPressure": 72.0,
            "SkinThickness": 54.0,
            "Insulin": 0.0,
            "BMI": 36.6
          },
          {
            "Pregnancies": 13.0,
            "Glucose": 136.0,
            "BloodPressure": 70.0,
            "SkinThickness": 32.0,
            "Insulin": 110.0,
            "BMI": 37.1
          },
          {
            "Pregnancies": 13.0,
            "Glucose": 163.0,
            "BloodPressure": 72.0,
            "SkinThickness": 41.0,
            "Insulin": 114.0,
            "BMI": 40.9
          },
          {
            "Pregnancies": 13.0,
            "Glucose": 106.0,
            "BloodPressure": 70.0,
            "SkinThickness": 0.0,
            "Insulin": 0.0,
            "BMI": 34.2
          },
          {
            "Pregnancies": 13.0,
            "Glucose": 100.0,
            "BloodPressure": 78.0,
            "SkinThickness": 25.0,
            "Insulin": 184.0,
            "BMI": 36.6
          },
          {
            "Pregnancies": 13.0,
            "Glucose": 152.0,
            "BloodPressure": 90.0,
            "SkinThickness": 33.0,
            "Insulin": 29.0,
            "BMI": 26.8
          },
          {
            "Pregnancies": 13.0,
            "Glucose": 129.0,
            "BloodPressure": 35.0,
            "SkinThickness": 30.0,
            "Insulin": 0.0,
            "BMI": 39.9
          },
          {
            "Pregnancies": 13.0,
            "Glucose": 175.0,
            "BloodPressure": 62.0,
            "SkinThickness": 30.0,
            "Insulin": 0.0,
            "BMI": 33.6
          }
        ],
        "insight": "145.0 tops the list with 13.00 pregnancies. Reviewing these top performers can reveal the factors behind strong results."
      }
    ]
  }
}